SDF/SDF.py
SDF/__init__.py
Simplify_downloading_files_TG-0.0.1.dist-info/LICENSE
Simplify_downloading_files_TG-0.0.1.dist-info/METADATA
Simplify_downloading_files_TG-0.0.1.dist-info/WHEEL
Simplify_downloading_files_TG-0.0.1.dist-info/top_level.txt
Simplify_downloading_files_TG-0.0.1.dist-info/RECORD
