Metadata-Version: 2.1
Name: Simplify-downloading-files-TG
Version: 0.0.1
Summary: Simplify downloading files from Telegram for PyTelegramBotAPI
Home-page: https://github.com/ZhenyaGOTL/Simplify-dowloading-files
Author: Zhenya Ovchinnikov
License: UNKNOWN
Project-URL: Bug Tracker, https://github.com/ZhenyaGOTL/Simplify-dowloading-files/issues
Platform: UNKNOWN
Classifier: Programming Language :: Python :: 3
Classifier: License :: OSI Approved :: MIT License
Classifier: Operating System :: OS Independent
Requires-Python: >=3.6
License-File: LICENSE
Requires-Dist: Pillow
Requires-Dist: requests
